{"data":{"markdownRemark":{"html":"<p>\"React工作原理\"是一个讲React(版本: 16.8.4)实现原理的网站，作者\b是<a href=\"https://terry-su.github.io\">苏溪云</a>。  </p>\n<p>作者最热爱的技术栈之一就是React，很早之前就打算弄清楚其内部实现原理，从而更自由地使用它。经过很长一段时间研究，包括研读React官网所有文档，查阅相关文章资料，精读和调试React源码，之后将其整理成文档并发布到网上。如果你喜欢这个网站，欢迎Star。后续会更新更多React相关原理内容(Hooks, React Router等)。</p>\n<!--如果你也对如何实现一个迷你react感兴趣，强烈推荐[react官网教程](https://reactjs.org/docs/implementation-notes.html),-->\n<p>整站文档将以先整体再局部、简明概要的结构展现所有内容。值得注意的是，文档不会涉及react-native，而是通过更为常用的react-dom来展现原理。</p>","headings":[],"fields":{"slug":"/get-started/cn/"}}},"pageContext":{"isCreatedByStatefulCreatePages":false,"slug":"/get-started/cn/","rootPath":"/cn/","locale":"zh_CN","decoratedLocale":"cn","texts":{"siteTitle":"React工作原理","getStarted":"开始使用","metaDesc":"React原理 React工作原理 如何实现React React源码","home":{"introduction":"了解React在底层如何运转"}},"pathname":"/cn/get-started","categories":[{"label":"整体流程","href":"/cn/whole-flow"},{"label":"Fiber","href":"/cn/fiber"},{"label":"模块","foldable":true,"folded":false,"items":[{"label":"JSX","href":"/cn/jsx"},{"label":"为什么setState是异步的","href":"/cn/why-setstate-is-async"},{"label":"React事件系统是如何运作的","href":"/cn/how-react-event-system-works"}]}]}}